moat/cad/__init__.py
moat/cad/_cfg.yaml
moat/cad/_main.py
moat/cad/export.py
moat/cad/gridbox.py
moat/cad/lib.py
moat/cad/math.py
moat/cad/misc.py
moat/cad/things.py
moat/cad/thread.py
moat_cad-0.3.9.dist-info/licenses/LICENSE.txt
moat_cad-0.3.9.dist-info/METADATA
moat_cad-0.3.9.dist-info/WHEEL
moat_cad-0.3.9.dist-info/top_level.txt
moat_cad-0.3.9.dist-info/RECORD
