Metadata-Version: 2.4
Name: moat-cad
Version: 0.3.9
Summary: CAD files for various MoaT-related things
Author-email: Matthias Urlichs <matthias@urlichs.de>
Project-URL: homepage, https://m-o-a-t.org
Project-URL: repository, https://github.com/M-o-a-T/moat
Keywords: MoaT
Classifier: Intended Audience :: Developers
Classifier: Programming Language :: Python :: 3
Classifier: Framework :: AsyncIO
Classifier: Framework :: Trio
Classifier: Framework :: AnyIO
Classifier: Development Status :: 4 - Beta
Requires-Python: >=3.10
License-File: LICENSE.txt
Requires-Dist: anyio~=4.0
Requires-Dist: cadquery~=2.0
Requires-Dist: moat-lib-config~=0.1.0
Requires-Dist: moat-lib-run~=0.1.0
Requires-Dist: moat-util~=0.61.1
Dynamic: license-file
